wordman/__init__.py
wordman/cli/__init__.py
wordman/cli/main.py
wordman/core/__init__.py
wordman/core/database.py
wordman/core/word_operations.py
wordman-0.1.1.dist-info/METADATA
wordman-0.1.1.dist-info/WHEEL
wordman-0.1.1.dist-info/entry_points.txt
wordman-0.1.1.dist-info/licenses/LICENSE
wordman-0.1.1.dist-info/RECORD
